ohmly/__init__.py
ohmly/catenary.py
ohmly/conductor.py
ohmly/conductor_db
ohmly/constants.py
ohmly/mech.py
ohmly/utils.py
ohmly-0.0.17.dist-info/METADATA
ohmly-0.0.17.dist-info/WHEEL
ohmly-0.0.17.dist-info/licenses/LICENSE
ohmly-0.0.17.dist-info/RECORD
