Metadata-Version: 2.4
Name: ohmly
Version: 0.0.17
Summary: An electrical and mechanical analysis tool of overhead conductors.
License-Expression: MIT
License-File: LICENSE
Author: Axel Rodríguez Chang
Author-email: axelrogg@icloud.com
Requires-Python: >=3.9
Classifier: Programming Language :: Python :: 3
Classifier: Programming Language :: Python :: 3.9
Classifier: Programming Language :: Python :: 3.10
Classifier: Programming Language :: Python :: 3.11
Classifier: Programming Language :: Python :: 3.12
Classifier: Programming Language :: Python :: 3.13
Classifier: Programming Language :: Python :: 3.14
Requires-Dist: rich (>=14.2.0,<15.0.0)
Project-URL: Homepage, https://github.com/axelrogg/ohmly
Project-URL: Issues, https://github.com/axelrogg/ohmly/issues
